dnsupdater/__init__.py
dnsupdater/__main__.py
dnsupdater/dnsupdater.py
dnsupdater/sns_notify.py
r53ddns/__init__.py
r53ddns/__main__.py
r53ddns/r53ddns.py
r53ddns/sns_notify.py
r53ddns-0.1.0b3.dist-info/LICENSE.txt
r53ddns-0.1.0b3.dist-info/METADATA
r53ddns-0.1.0b3.dist-info/WHEEL
r53ddns-0.1.0b3.dist-info/entry_points.txt
r53ddns-0.1.0b3.dist-info/top_level.txt
r53ddns-0.1.0b3.dist-info/RECORD
