Metadata-Version: 2.1
Name: r53ddns
Version: 0.1.0b3
Summary: Route 53 Dynamic DNS Update Client
Home-page: UNKNOWN
Author: Zachery Brady
Author-email: bradyzp@dynamicgravitysytems.com
License: UNKNOWN
Platform: UNKNOWN
Classifier: Development Status :: 3 - Alpha
Classifier: License :: OSI Approved :: MIT License
Classifier: Natural Language :: English
Classifier: Operating System :: POSIX :: Linux
Classifier: Operating System :: Microsoft :: Windows
Classifier: Programming Language :: Python :: 3.6
Requires-Dist: boto3 (==1.9.66)
